bespokelabs/__init__.py
bespokelabs/curator/__init__.py
bespokelabs/curator/agent/__init__.py
bespokelabs/curator/agent/agent.py
bespokelabs/curator/agent/agent_response.py
bespokelabs/curator/agent/processor.py
bespokelabs/curator/blocks/__init__.py
bespokelabs/curator/blocks/raft.py
bespokelabs/curator/blocks/simplestrat.py
bespokelabs/curator/client.py
bespokelabs/curator/code_executor/__init__.py
bespokelabs/curator/code_executor/code_execution_backend/_factory.py
bespokelabs/curator/code_executor/code_execution_backend/base_backend.py
bespokelabs/curator/code_executor/code_execution_backend/docker_backend.py
bespokelabs/curator/code_executor/code_execution_backend/e2b_backend.py
bespokelabs/curator/code_executor/code_execution_backend/multiprocessing_backend.py
bespokelabs/curator/code_executor/code_execution_backend/ray_backend.py
bespokelabs/curator/code_executor/code_executor.py
bespokelabs/curator/code_executor/code_formatter.py
bespokelabs/curator/code_executor/db.py
bespokelabs/curator/code_executor/tracker.py
bespokelabs/curator/code_executor/types.py
bespokelabs/curator/constants.py
bespokelabs/curator/cost.py
bespokelabs/curator/db.py
bespokelabs/curator/file_utilities.py
bespokelabs/curator/hf_card_template.py
bespokelabs/curator/install_ui.py
bespokelabs/curator/llm/llm.py
bespokelabs/curator/llm/prompt_formatter.py
bespokelabs/curator/log.py
bespokelabs/curator/misc.py
bespokelabs/curator/request_processor/__init__.py
bespokelabs/curator/request_processor/_default_rate_limits.json
bespokelabs/curator/request_processor/_factory.py
bespokelabs/curator/request_processor/base_request_processor.py
bespokelabs/curator/request_processor/batch/anthropic_batch_request_processor.py
bespokelabs/curator/request_processor/batch/base_batch_request_processor.py
bespokelabs/curator/request_processor/batch/gemini_batch_request_processor.py
bespokelabs/curator/request_processor/batch/mistral_batch_request_processor.py
bespokelabs_curator-0.1.25.dist-info/LICENSE
bespokelabs_curator-0.1.25.dist-info/METADATA
bespokelabs_curator-0.1.25.dist-info/WHEEL
bespokelabs_curator-0.1.25.dist-info/entry_points.txt
bespokelabs_curator-0.1.25.dist-info/RECORD
