Metadata-Version: 2.3
Name: bespokelabs-curator
Version: 0.1.25
Summary: Bespoke Labs Curator
License: Apache-2.0
Keywords: ai,curator,bespoke
Author: Bespoke Labs
Author-email: company@bespokelabs.ai
Requires-Python: >=3.10,<4.0
Classifier: License :: OSI Approved :: Apache Software License
Classifier: Programming Language :: Python :: 3
Classifier: Programming Language :: Python :: 3.10
Classifier: Programming Language :: Python :: 3.11
Classifier: Programming Language :: Python :: 3.12
Classifier: Programming Language :: Python :: 3.13
Provides-Extra: code-execution
Provides-Extra: vllm
Requires-Dist: aiodocker (>=0.24.0,<0.25.0) ; extra == "code-execution"
Requires-Dist: aiofiles (>=22.0,<24.0)
Requires-Dist: anthropic (>=0.47.2,<0.48.0)
Requires-Dist: datasets (>=3.0.2,<4.0.0)
Requires-Dist: e2b-code-interpreter (==1.0.3) ; extra == "code-execution"
Requires-Dist: instructor (>=1.6.3,<2.0.0)
Requires-Dist: litellm (==1.61.3)
Requires-Dist: matplotlib (>=3.9.2,<4.0.0)
Requires-Dist: mistralai (>=1.5.1,<2.0.0)
Requires-Dist: nest-asyncio (>=1.6.0,<2.0.0)
Requires-Dist: pandas (==2.2.2)
Requires-Dist: posthog (>=3.11.0,<4.0.0)
Requires-Dist: pydantic (>=2.9.2)
Requires-Dist: ray (>=2.41.0,<3.0.0) ; extra == "code-execution"
Requires-Dist: rich (>=13.7.0,<14.0.0)
Requires-Dist: tiktoken (>=0.7.0)
Requires-Dist: tqdm (>=4.67.0,<5.0.0)
Requires-Dist: vertexai (==1.71.1)
Requires-Dist: vllm (>=0.6.3,<0.7.0) ; extra == "vllm"
Requires-Dist: xxhash (>=3.5.0,<4.0.0)
Project-URL: Homepage, https://github.com/bespokelabsai/curator
Project-URL: Repository, https://github.com/bespokelabsai/curator
